directmessages/__init__.py
directmessages/admin.py
directmessages/apps.py
directmessages/models.py
directmessages/services.py
directmessages/signals.py
directmessages/tests.py
directmessages/migrations/0001_initial.py
directmessages/migrations/0002_auto_20190821_1010.py
directmessages/migrations/0003_message_sender_user.py
directmessages/migrations/__init__.py
django_full_directmessages-0.9.17.dist-info/METADATA
django_full_directmessages-0.9.17.dist-info/RECORD
django_full_directmessages-0.9.17.dist-info/WHEEL
django_full_directmessages-0.9.17.dist-info/top_level.txt
