Metadata-Version: 2.1
Name: django-full-directmessages
Version: 0.9.17
Summary: Django-Directmessages is a low-level and easy-to-use Django App to manage simple directmessages.
Home-page: UNKNOWN
Author: Dominic Monn
Author-email: yacine@grad4.com
License: BSD License
Platform: OS Independent
Classifier: Environment :: Web Environment
Classifier: Framework :: Django
Classifier: Intended Audience :: Developers
Classifier: License :: OSI Approved :: BSD License
Classifier: Operating System :: OS Independent
Classifier: Programming Language :: Python
Classifier: Programming Language :: Python :: 2
Classifier: Programming Language :: Python :: 3
Classifier: Topic :: Software Development :: Libraries :: Application Frameworks
Classifier: Topic :: Internet :: WWW/HTTP :: Dynamic Content
Requires-Dist: Django (>=1.5)
